{
  "info": {
    "name": "Student Information System API",
    "description": "Comprehensive API collection for the University Student Information System",
    "version": "1.0.0",
    "schema": "https://schema.getpostman.com/json/collection/v2.1.0/collection.json"
  },
  "variable": [
    {
      "key": "baseUrl",
      "value": "{{base_url}}",
      "type": "string"
    },
    {
      "key": "accessToken",
      "value": "",
      "type": "string"
    },
    {
      "key": "refreshToken",
      "value": "",
      "type": "string"
    },
    {
      "key": "userId",
      "value": "",
      "type": "string"
    },
    {
      "key": "studentId",
      "value": "",
      "type": "string"
    }
  ],
  "auth": {
    "type": "bearer",
    "bearer": [
      {
        "key": "token",
        "value": "{{accessToken}}",
        "type": "string"
      }
    ]
  },
  "event": [
    {
      "listen": "prerequest",
      "script": {
        "type": "text/javascript",
        "exec": [
          "// Auto-refresh token if expired",
          "const accessToken = pm.collectionVariables.get('accessToken');",
          "if (accessToken) {",
          "  const payload = JSON.parse(atob(accessToken.split('.')[1]));",
          "  const exp = payload.exp * 1000;",
          "  if (Date.now() >= exp) {",
          "    const refreshToken = pm.collectionVariables.get('refreshToken');",
          "    if (refreshToken) {",
          "      pm.sendRequest({",
          "        url: pm.collectionVariables.get('baseUrl') + '/api/auth/refresh',",
          "        method: 'POST',",
          "        header: { 'Content-Type': 'application/json' },",
          "        body: { mode: 'raw', raw: JSON.stringify({ refreshToken }) }",
          "      }, function (err, res) {",
          "        if (!err && res.json().status === 'success') {",
          "          pm.collectionVariables.set('accessToken', res.json().data.accessToken);",
          "        }",
          "      });",
          "    }",
          "  }",
          "}"
        ]
      }
    }
  ],
  "item": [
    {
      "name": "Authentication",
      "item": [
        {
          "name": "Login",
          "request": {
            "method": "POST",
            "header": [{"key": "Content-Type", "value": "application/json"}],
            "body": {
              "mode": "raw",
              "raw": "{\n  \"email\": \"admin@university.edu\",\n  \"password\": \"admin123\"\n}"
            },
            "url": {
              "raw": "{{baseUrl}}/api/auth/login",
              "host": ["{{baseUrl}}"],
              "path": ["api", "auth", "login"]
            }
          },
          "event": [
            {
              "listen": "test",
              "script": {
                "exec": [
                  "pm.test('Login successful', function () {",
                  "  pm.response.to.have.status(200);",
                  "  const responseJson = pm.response.json();",
                  "  pm.collectionVariables.set('accessToken', responseJson.data.accessToken);",
                  "  pm.collectionVariables.set('refreshToken', responseJson.data.refreshToken);",
                  "  pm.collectionVariables.set('userId', responseJson.data.user._id);",
                  "});"
                ]
              }
            }
          ]
        },
        {
          "name": "Register",
          "request": {
            "method": "POST",
            "header": [{"key": "Content-Type", "value": "application/json"}],
            "body": {
              "mode": "raw",
              "raw": "{\n  \"firstName\": \"أحمد\",\n  \"lastName\": \"محمد\",\n  \"email\": \"ahmed@university.edu\",\n  \"password\": \"SecurePass123!\",\n  \"role\": \"student\",\n  \"phone\": \"+966501234567\"\n}"
            },
            "url": {
              "raw": "{{baseUrl}}/api/auth/register",
              "host": ["{{baseUrl}}"],
              "path": ["api", "auth", "register"]
            }
          }
        },
        {
          "name": "Get Profile",
          "request": {
            "method": "GET",
            "url": {
              "raw": "{{baseUrl}}/api/auth/profile",
              "host": ["{{baseUrl}}"],
              "path": ["api", "auth", "profile"]
            }
          }
        },
        {
          "name": "Update Profile",
          "request": {
            "method": "PATCH",
            "header": [{"key": "Content-Type", "value": "application/json"}],
            "body": {
              "mode": "raw",
              "raw": "{\n  \"firstName\": \"أحمد المحدث\",\n  \"phone\": \"+966501234999\"\n}"
            },
            "url": {
              "raw": "{{baseUrl}}/api/auth/profile",
              "host": ["{{baseUrl}}"],
              "path": ["api", "auth", "profile"]
            }
          }
        },
        {
          "name": "Change Password",
          "request": {
            "method": "PATCH",
            "header": [{"key": "Content-Type", "value": "application/json"}],
            "body": {
              "mode": "raw",
              "raw": "{\n  \"currentPassword\": \"admin123\",\n  \"newPassword\": \"newAdmin123!\"\n}"
            },
            "url": {
              "raw": "{{baseUrl}}/api/auth/change-password",
              "host": ["{{baseUrl}}"],
              "path": ["api", "auth", "change-password"]
            }
          }
        },
        {
          "name": "Refresh Token",
          "request": {
            "method": "POST",
            "header": [{"key": "Content-Type", "value": "application/json"}],
            "body": {
              "mode": "raw",
              "raw": "{\n  \"refreshToken\": \"{{refreshToken}}\"\n}"
            },
            "url": {
              "raw": "{{baseUrl}}/api/auth/refresh",
              "host": ["{{baseUrl}}"],
              "path": ["api", "auth", "refresh"]
            }
          }
        },
        {
          "name": "Logout",
          "request": {
            "method": "POST",
            "url": {
              "raw": "{{baseUrl}}/api/auth/logout",
              "host": ["{{baseUrl}}"],
              "path": ["api", "auth", "logout"]
            }
          }
        }
      ]
    }
  ]
}